README.md
setup.py
ptx_api/__init__.py
ptx_api/api.py
ptx_api.egg-info/PKG-INFO
ptx_api.egg-info/SOURCES.txt
ptx_api.egg-info/dependency_links.txt
ptx_api.egg-info/requires.txt
ptx_api.egg-info/top_level.txt