Metadata-Version: 2.1
Name: ptx-api
Version: 1.0.3
Summary: A Python Module for get data from PTX.
Home-page: https://github.com/PinLin/ptx_api
Author: pinlin
Author-email: moneycat711@gmail.com
License: MIT License
Platform: all
